http_cat/__init__.py
httpcats_and_httpdog/__init__.py
httpcats_and_httpdog-0.1.dist-info/LICENSE
httpcats_and_httpdog-0.1.dist-info/METADATA
httpcats_and_httpdog-0.1.dist-info/WHEEL
httpcats_and_httpdog-0.1.dist-info/top_level.txt
httpcats_and_httpdog-0.1.dist-info/RECORD
