Metadata-Version: 2.1
Name: httpcats-and-httpdog
Version: 0.1
Summary: A simple httpcat and httpdog call function returns image data when called
Home-page: https://github.com/cacaview/http_cat
Author: cacaview
Author-email: cacaview@foxmail.com
License: MIT
Classifier: Development Status :: 3 - Alpha
Classifier: Intended Audience :: Developers
Classifier: License :: OSI Approved :: MIT License
Classifier: Programming Language :: Python
Classifier: Programming Language :: Python :: 3
Classifier: Programming Language :: Python :: 3.10
Classifier: Topic :: Software Development :: Libraries :: Python Modules
License-File: LICENSE
Requires-Dist: requests
